eeglabio/__init__.py
eeglabio/_version.py
eeglabio/epochs.py
eeglabio/raw.py
eeglabio/utils.py
eeglabio-0.1.3.dist-info/licenses/LICENSE
eeglabio-0.1.3.dist-info/METADATA
eeglabio-0.1.3.dist-info/WHEEL
eeglabio-0.1.3.dist-info/top_level.txt
eeglabio-0.1.3.dist-info/RECORD
