Metadata-Version: 2.4
Name: eeglabio
Version: 0.1.3
Summary: I/O support for EEGLAB files in Python
Home-page: https://github.com/jackz314/eeglabio
Download-URL: https://github.com/jackz314/eeglabio
Author: Jack Zhang
Author-email: zhangmengyu10@gmail.com
License: BSD (3-clause)
Project-URL: Source, https://github.com/jackz314/eeglabio
Project-URL: Tracker, https://github.com/jackz314/eeglabio/issues
Keywords: EEG MEG MNE EEGLAB
Classifier: Programming Language :: Python :: 3
Classifier: License :: OSI Approved :: BSD License
Classifier: Operating System :: OS Independent
Requires-Python: >=3.7
License-File: LICENSE
Requires-Dist: numpy
Requires-Dist: scipy
Dynamic: author
Dynamic: author-email
Dynamic: classifier
Dynamic: description
Dynamic: description-content-type
Dynamic: download-url
Dynamic: home-page
Dynamic: keywords
Dynamic: license
Dynamic: license-file
Dynamic: project-url
Dynamic: requires-dist
Dynamic: requires-python
Dynamic: summary
